NiuLab_download_Youtube_shorts/NiuLab_download_Youtube_shorts.py
NiuLab_download_Youtube_shorts/__init__.py
NiuLab_download_YouTube_shorts-1.0.2.dist-info/LICENSE
NiuLab_download_YouTube_shorts-1.0.2.dist-info/METADATA
NiuLab_download_YouTube_shorts-1.0.2.dist-info/WHEEL
NiuLab_download_YouTube_shorts-1.0.2.dist-info/top_level.txt
NiuLab_download_YouTube_shorts-1.0.2.dist-info/RECORD
