Metadata-Version: 2.1
Name: NiuLab-download-YouTube-shorts
Version: 1.0.2
Summary: Downloads Youtube Videos
Author-email: "Shuo Niu, Abhisan Ghimire" <invictuscreatesanapp@gmail.com>
License: MIT License        
Classifier: Programming Language :: Python :: 3
Classifier: License :: OSI Approved :: MIT License
Classifier: Operating System :: OS Independent
Requires-Python: >=3.7
License-File: LICENSE
